[{"content": " ", "type": "box", "className": "arousal rn1", "id": 101, "group": 1, "start": "2019-02-02 00:23:20"}, {"content": " ", "type": "box", "className": "arousal rn1", "id": 102, "group": 1, "start": "2019-02-02 00:30:09"}, {"content": " ", "type": "box", "className": "arousal rn1", "id": 103, "group": 1, "start": "2019-02-02 00:35:45"}, {"content": " ", "type": "box", "className": "arousal rn1", "id": 104, "group": 1, "start": "2019-02-02 00:43:53"}, {"content": " ", "type": "box", "className": "arousal rn3", "id": 301, "group": 3, "start": "2019-02-02 00:06:57"}, {"content": " ", "type": "box", "className": "arousal rn3", "id": 302, "group": 3, "start": "2019-02-02 00:24:45"}, {"content": " ", "type": "box", "className": "arousal rn3", "id": 303, "group": 3, "start": "2019-02-02 01:06:05"}, {"content": " ", "type": "box", "className": "arousal rn4", "id": 401, "group": 4, "start": "2019-02-02 00:48:48"}]